{"name": "Blaise Pascal", "born": "19 June 1623", "born_place": "Clermont (now Clermont-Ferrand), Auvergne, France", "died": "19 August 1662", "died_place": "Paris, France", "summary": "Blaise Pascal was a very influential French mathematician and philosopher who contributed to many areas of mathematics. He worked on conic sections and projective geometry and in correspondence with Fermat he laid the foundations for the theory of probability.", "link": "https://mathshistory.st-andrews.ac.uk/Biographies/Pascal/"}